edaflow/__init__.py
edaflow/display.py
edaflow/analysis/__init__.py
edaflow/analysis/core.py
edaflow/analysis/missing_data.py
edaflow/ml/__init__.py
edaflow/ml/artifacts.py
edaflow/ml/config.py
edaflow/ml/curves.py
edaflow/ml/leaderboard.py
edaflow/ml/tuning.py
edaflow-0.17.1.dist-info/licenses/LICENSE
edaflow-0.17.1.dist-info/METADATA
edaflow-0.17.1.dist-info/WHEEL
edaflow-0.17.1.dist-info/top_level.txt
edaflow-0.17.1.dist-info/RECORD
