Metadata-Version: 2.4
Name: edaflow
Version: 0.17.1
Summary: A Python package for exploratory data analysis workflows with universal dark mode compatibility
Author-email: Evan Low <evan.low@illumetechnology.com>
Maintainer-email: Evan Low <evan.low@illumetechnology.com>
License-Expression: MIT
Project-URL: Homepage, https://github.com/evanlow/edaflow
Project-URL: Documentation, https://edaflow.readthedocs.io
Project-URL: Repository, https://github.com/evanlow/edaflow.git
Project-URL: Bug Tracker, https://github.com/evanlow/edaflow/issues
Project-URL: Changelog, https://github.com/evanlow/edaflow/blob/main/CHANGELOG.md
Project-URL: Source Code, https://github.com/evanlow/edaflow
Keywords: data-analysis,eda,exploratory-data-analysis,data-science,visualization
Classifier: Development Status :: 3 - Alpha
Classifier: Intended Audience :: Developers
Classifier: Intended Audience :: Science/Research
Classifier: Operating System :: OS Independent
Classifier: Programming Language :: Python :: 3
Classifier: Programming Language :: Python :: 3.8
Classifier: Programming Language :: Python :: 3.9
Classifier: Programming Language :: Python :: 3.10
Classifier: Programming Language :: Python :: 3.11
Classifier: Programming Language :: Python :: 3.12
Classifier: Topic :: Scientific/Engineering :: Information Analysis
Classifier: Topic :: Software Development :: Libraries :: Python Modules
Requires-Python: >=3.8
License-File: LICENSE
Requires-Dist: pandas>=1.5.0
Requires-Dist: numpy>=1.21.0
Requires-Dist: matplotlib>=3.5.0
Requires-Dist: seaborn>=0.11.0
Requires-Dist: scipy>=1.7.0
Requires-Dist: missingno>=0.5.0
Requires-Dist: plotly>=5.0.0
Requires-Dist: scikit-learn>=1.0.0
Requires-Dist: statsmodels>=0.13.0
Requires-Dist: Pillow>=8.0.0
Requires-Dist: rich>=13.0.0
Provides-Extra: cv
Requires-Dist: opencv-python>=4.5.0; extra == "cv"
Requires-Dist: scikit-image>=0.19.0; extra == "cv"
Provides-Extra: dev
Requires-Dist: pytest>=6.0; extra == "dev"
Requires-Dist: pytest-cov; extra == "dev"
Requires-Dist: black; extra == "dev"
Requires-Dist: flake8; extra == "dev"
Requires-Dist: isort; extra == "dev"
Requires-Dist: mypy; extra == "dev"
Requires-Dist: pre-commit; extra == "dev"
Provides-Extra: docs
Requires-Dist: sphinx; extra == "docs"
Requires-Dist: sphinx-rtd-theme; extra == "docs"
Requires-Dist: myst-parser; extra == "docs"
Provides-Extra: test
Requires-Dist: pytest>=6.0; extra == "test"
Requires-Dist: pytest-cov; extra == "test"
Requires-Dist: pytest-mock; extra == "test"
Dynamic: license-file
